bdc/__init__.py
bdc/bdc
bdc/bdc-gui
bdc/bootableDiskCreator.py
bdc/dependencyChecker.py
bdc/gui.py
bdc/tests.py
bdc-1.0.6.data/scripts/bdc
bdc-1.0.6.data/scripts/bdc-gui
bdc-1.0.6.dist-info/LICENSE
bdc-1.0.6.dist-info/METADATA
bdc-1.0.6.dist-info/WHEEL
bdc-1.0.6.dist-info/top_level.txt
bdc-1.0.6.dist-info/RECORD
