Metadata-Version: 2.1
Name: bdc
Version: 1.0.6
Summary: bootable install media creator
Home-page: https://www.github.com/adamjenkins1/BootableDiskCreator
Author: Adam Jenkins
Author-email: adamjenkins1701@gmail.com
License: UNKNOWN
Platform: Linux
Classifier: Programming Language :: Python :: 3.5
Classifier: Programming Language :: Python :: 3.6
Classifier: License :: OSI Approved :: MIT License
Classifier: Operating System :: POSIX :: Linux
Requires-Python: ~=3.5
Requires-Dist: PyQt5 (==5.11.3)
